Workbook

Sheet Raw Data
A1: BEVERAGES INDIA — RAW SALES DATA | FY 2023 | Analytics Portfolio Project
A2: Row ID | B2: Month | C2: Month Num | D2: SKU Category | E2: Brand | F2: Region | G2: Units Sold | H2: Unit Price (Rs) | I2: Gross Revenue (Rs) | J2: Discount % | K2: Net Revenue (Rs) | L2: Promotion | M2: Customer Rating
A3: 1 | B3: Jan-23 | C3: 1 | D3: Cola | E3: ColaMax | F3: North India | G3: 1491 | H3: 45 | I3: 67095 | J3: 0 | K3: 67095 | L3: No | M3: 4
A4: 2 | B4: Jan-23 | C4: 1 | D4: Cola | E4: ColaMax | F4: South India | G4: 1746 | H4: 45 | I4: 78570 | J4: 0 | K4: 78570 | L4: No | M4: 4.5
A5: 3 | B5: Jan-23 | C5: 1 | D5: Cola | E5: ColaMax | F5: East India | G5: 1212 | H5: 45 | I5: 54540 | J5: 0 | K5: 54540 | L5: No | M5: 4.1
A6: 4 | B6: Jan-23 | C6: 1 | D6: Cola | E6: ColaMax | F6: West India | G6: 1503 | H6: 45 | I6: 67635 | J6: 10 | K6: 60872 | L6: Yes | M6: 4.4
A7: 5 | B7: Jan-23 | C7: 1 | D7: Energy Drink | E7: Monster | F7: North India | G7: 885 | H7: 125 | I7: 110625 | J7: 0 | K7: 110625 | L7: No | M7: 4.5
A8: 6 | B8: Jan-23 | C8: 1 | D8: Energy Drink | E8: Monster | F8: South India | G8: 816 | H8: 125 | I8: 102000 | J8: 0 | K8: 102000 | L8: No | M8: 4
A9: 7 | B9: Jan-23 | C9: 1 | D9: Energy Drink | E9: Monster | F9: East India | G9: 715 | H9: 125 | I9: 89375 | J9: 0 | K9: 89375 | L9: No | M9: 3.8
A10: 8 | B10: Jan-23 | C10: 1 | D10: Energy Drink | E10: Monster | F10: West India | G10: 760 | H10: 125 | I10: 95000 | J10: 0 | K10: 95000 | L10: No | M10: 3.9
A11: 9 | B11: Jan-23 | C11: 1 | D11: Juice | E11: Tropika | F11: North India | G11: 930 | H11: 80 | I11: 74400 | J11: 0 | K11: 74400 | L11: No | M11: 4.1
A12: 10 | B12: Jan-23 | C12: 1 | D12: Juice | E12: Tropika | F12: South India | G12: 971 | H12: 80 | I12: 77680 | J12: 0 | K12: 77680 | L12: No | M12: 3.9
A13: 11 | B13: Jan-23 | C13: 1 | D13: Juice | E13: Tropika | F13: East India | G13: 829 | H13: 80 | I13: 66320 | J13: 20 | K13: 53056 | L13: Yes | M13: 4.9
A14: 12 | B14: Jan-23 | C14: 1 | D14: Juice | E14: Tropika | F14: West India | G14: 994 | H14: 80 | I14: 79520 | J14: 0 | K14: 79520 | L14: No | M14: 4.7
... A290: 288 | B290: Dec-23 | C290: 12 | D290: Tea | E290: TeaLeaf | F290: West India | G290: 1395 | H290: 35 | I290: 48825 | J290: 0 | K290: 48825 | L290: No | M290: 4.8

Sheet Pivot Analysis
A1: PIVOT ANALYSIS — Beverages India FY 2023 | Sales by Category, Region & Month
A3: NET REVENUE BY CATEGORY & REGION
A4: SKU Category | B4: North India | C4: South India | D4: East India | E4: West India | F4: Grand Total
A5: Cola | B5: 1071189 | C5: 1101010 | D5: 874869 | E5: 997653 | F5: 4044721
A6: Energy Drink | B6: 1485425 | C6: 1548337 | D6: 1229650 | E6: 1471900 | F6: 5735312
A7: Juice | B7: 1181620 | C7: 1208400 | D7: 906148 | E7: 1176180 | F7: 4472348
A8: Water | B8: 790650 | C8: 746526 | D8: 578052 | E8: 715009 | F8: 2830237
A9: Sports Drink | B9: 833580 | C9: 872712 | D9: 704898 | E9: 812520 | F9: 3223710
A10: Tea | B10: 692742 | C10: 658975 | D10: 506133 | E10: 650591 | F10: 2508441
A11: Grand Total | B11: 6055206 | C11: 6135960 | D11: 4799750 | E11: 5823853 | F11: 22814769
A14: MONTHLY NET REVENUE BY CATEGORY
A15: SKU Category | B15: Jan-23 | C15: Feb-23 | D15: Mar-23 | E15: Apr-23 | F15: May-23 | G15: Jun-23 | H15: Jul-23 | I15: Aug-23 | J15: Sep-23 | K15: Oct-23 | L15: Nov-23 | M15: Dec-23 | N15: Total
A16: Cola | B16: 261077 | C16: 272340 | D16: 301275 | E16: 332233 | F16: 402435 | G16: 398720 | H16: 383301 | I16: 426555 | J16: 360720 | K16: 331105 | L16: 267862 | M16: 307098 | N16: 4044721
A17: Energy Drink | B17: 397000 | C17: 351750 | D17: 398100 | E17: 475125 | F17: 522075 | G17: 629025 | H17: 579375 | I17: 582625 | J17: 503500 | K17: 451737 | L17: 403500 | M17: 441500 | N17: 5735312
A18: Juice | B18: 284656 | C18: 292880 | D18: 303532 | E18: 361084 | F18: 419840 | G18: 475220 | H18: 500960 | I18: 420364 | J18: 375060 | K18: 375320 | L18: 346640 | M18: 316792 | N18: 4472348
A19: Water | B19: 179071 | C19: 185924 | D19: 208888 | E19: 237629 | F19: 255239 | G19: 329025 | H19: 288175 | I19: 276700 | J19: 231211 | K19: 218450 | L19: 198375 | M19: 221550 | N19: 2830237
A20: Sports Drink | B20: 203373 | C20: 193635 | D20: 250470 | E20: 250704 | F20: 308700 | G20: 348552 | H20: 322020 | I20: 322380 | J20: 278766 | K20: 258480 | L20: 235440 | M20: 251190 | N20: 3223710
A21: Tea | B21: 165305 | C21: 158550 | D21: 181790 | E21: 212894 | F21: 231553 | G21: 261321 | H21: 250358 | I21: 239575 | J21: 223575 | K21: 215880 | L21: 179235 | M21: 188405 | N21: 2508441

Sheet KPI Tracker
A1: KPI TRACKER — Beverages India FY 2023 | Revenue vs Target | Market Share | MoM Growth
A3: MONTHLY PERFORMANCE TRACKER — NET REVENUE vs TARGET
A4: Month | B4: Month Num | C4: Actual Revenue | D4: Target Revenue | E4: vs Target | F4: Attainment % | G4: MoM Growth % | H4: YTD Actual | I4: YTD Target | J4: Status
A5: Jan-23 | B5: 1 | C5: =SUMIFS('Raw Data'!K:K,'Raw Data'!B:B,A5) -> 1490482 | D5: 1490482 | E5: =C5-D5 -> 0 | F5: =IFERROR(C5/D5,0) -> 1 | H5: =SUM($C$5:C5) -> 1490482 | I5: =SUM($D$5:D5) -> 1490482 | J5: =IF(F5>=1,"✅ ON TRACK",IF(F5>=0.92,"⚠️ AT RISK","❌ BELOW")) -> ✅ ON TRACK
A6: Feb-23 | B6: 2 | C6: =SUMIFS('Raw Data'!K:K,'Raw Data'!B:B,A6) -> 1455079 | D6: 1565006 | E6: =C6-D6 -> -109927 | F6: =IFERROR(C6/D6,0) -> 0.92975937 | G6: =IFERROR((C6-C5)/C5,0) -> -0.023752719 | H6: =SUM($C$5:C6) -> 2945561 | I6: =SUM($D$5:D6) -> 3055488 | J6: =IF(F6>=1,"✅ ON TRACK",IF(F6>=0.92,"⚠️ AT RISK","❌ BELOW")) -> ⚠️ AT RISK
A7: Mar-23 | B7: 3 | C7: =SUMIFS('Raw Data'!K:K,'Raw Data'!B:B,A7) -> 1644055 | D7: 1643256 | E7: =C7-D7 -> 799 | F7: =IFERROR(C7/D7,0) -> 1.0004862 | G7: =IFERROR((C7-C6)/C6,0) -> 0.12987336 | H7: =SUM($C$5:C7) -> 4589616 | I7: =SUM($D$5:D7) -> 4698744 | J7: =IF(F7>=1,"✅ ON TRACK",IF(F7>=0.92,"⚠️ AT RISK","❌ BELOW")) -> ✅ ON TRACK
A8: Apr-23 | B8: 4 | C8: =SUMIFS('Raw Data'!K:K,'Raw Data'!B:B,A8) -> 1869669 | D8: 1725419 | E8: =C8-D8 -> 144250 | F8: =IFERROR(C8/D8,0) -> 1.0836029 | G8: =IFERROR((C8-C7)/C7,0) -> 0.1372302 | H8: =SUM($C$5:C8) -> 6459285 | I8: =SUM($D$5:D8) -> 6424163 | J8: =IF(F8>=1,"✅ ON TRACK",IF(F8>=0.92,"⚠️ AT RISK","❌ BELOW")) -> ✅ ON TRACK
A9: May-23 | B9: 5 | C9: =SUMIFS('Raw Data'!K:K,'Raw Data'!B:B,A9) -> 2139842 | D9: 1811690 | E9: =C9-D9 -> 328152 | F9: =IFERROR(C9/D9,0) -> 1.1811303 | G9: =IFERROR((C9-C8)/C8,0) -> 0.14450312 | H9: =SUM($C$5:C9) -> 8599127 | I9: =SUM($D$5:D9) -> 8235853 | J9: =IF(F9>=1,"✅ ON TRACK",IF(F9>=0.92,"⚠️ AT RISK","❌ BELOW")) -> ✅ ON TRACK
A10: Jun-23 | B10: 6 | C10: =SUMIFS('Raw Data'!K:K,'Raw Data'!B:B,A10) -> 2441863 | D10: 1902275 | E10: =C10-D10 -> 539588 | F10: =IFERROR(C10/D10,0) -> 1.283654 | G10: =IFERROR((C10-C9)/C9,0) -> 0.14114173 | H10: =SUM($C$5:C10) -> 11040990 | I10: =SUM($D$5:D10) -> 10138128 | J10: =IF(F10>=1,"✅ ON TRACK",IF(F10>=0.92,"⚠️ AT RISK","❌ BELOW")) -> ✅ ON TRACK
A11: Jul-23 | B11: 7 | C11: =SUMIFS('Raw Data'!K:K,'Raw Data'!B:B,A11) -> 2324189 | D11: 1997388 | E11: =C11-D11 -> 326801 | F11: =IFERROR(C11/D11,0) -> 1.1636142 | G11: =IFERROR((C11-C10)/C10,0) -> -0.048190255 | H11: =SUM($C$5:C11) -> 13365179 | I11: =SUM($D$5:D11) -> 12135516 | J11: =IF(F11>=1,"✅ ON TRACK",IF(F11>=0.92,"⚠️ AT RISK","❌ BELOW")) -> ✅ ON TRACK
A12: Aug-23 | B12: 8 | C12: =SUMIFS('Raw Data'!K:K,'Raw Data'!B:B,A12) -> 2268199 | D12: 2097258 | E12: =C12-D12 -> 170941 | F12: =IFERROR(C12/D12,0) -> 1.0815069 | G12: =IFERROR((C12-C11)/C11,0) -> -0.024090123 | H12: =SUM($C$5:C12) -> 15633378 | I12: =SUM($D$5:D12) -> 14232774 | J12: =IF(F12>=1,"✅ ON TRACK",IF(F12>=0.92,"⚠️ AT RISK","❌ BELOW")) -> ✅ ON TRACK
A13: Sep-23 | B13: 9 | C13: =SUMIFS('Raw Data'!K:K,'Raw Data'!B:B,A13) -> 1972832 | D13: 2202121 | E13: =C13-D13 -> -229289 | F13: =IFERROR(C13/D13,0) -> 0.89587811 | G13: =IFERROR((C13-C12)/C12,0) -> -0.13022094 | H13: =SUM($C$5:C13) -> 17606210 | I13: =SUM($D$5:D13) -> 16434895 | J13: =IF(F13>=1,"✅ ON TRACK",IF(F13>=0.92,"⚠️ AT RISK","❌ BELOW")) -> ❌ BELOW
A14: Oct-23 | B14: 10 | C14: =SUMIFS('Raw Data'!K:K,'Raw Data'!B:B,A14) -> 1850972 | D14: 2312227 | E14: =C14-D14 -> -461255 | F14: =IFERROR(C14/D14,0) -> 0.80051483 | G14: =IFERROR((C14-C13)/C13,0) -> -0.061769071 | H14: =SUM($C$5:C14) -> 19457182 | I14: =SUM($D$5:D14) -> 18747122 | J14: =IF(F14>=1,"✅ ON TRACK",IF(F14>=0.92,"⚠️ AT RISK","❌ BELOW")) -> ❌ BELOW
A15: Nov-23 | B15: 11 | C15: =SUMIFS('Raw Data'!K:K,'Raw Data'!B:B,A15) -> 1631052 | D15: 2427838 | E15: =C15-D15 -> -796786 | F15: =IFERROR(C15/D15,0) -> 0.67181253 | G15: =IFERROR((C15-C14)/C14,0) -> -0.11881325 | H15: =SUM($C$5:C15) -> 21088234 | I15: =SUM($D$5:D15) -> 21174960 | J15: =IF(F15>=1,"✅ ON TRACK",IF(F15>=0.92,"⚠️ AT RISK","❌ BELOW")) -> ❌ BELOW
A16: Dec-23 | B16: 12 | C16: =SUMIFS('Raw Data'!K:K,'Raw Data'!B:B,A16) -> 1726535 | D16: 2549230 | E16: =C16-D16 -> -822695 | F16: =IFERROR(C16/D16,0) -> 0.67727706 | G16: =IFERROR((C16-C15)/C15,0) -> 0.058540745 | H16: =SUM($C$5:C16) -> 22814769 | I16: =SUM($D$5:D16) -> 23724190 | J16: =IF(F16>=1,"✅ ON TRACK",IF(F16>=0.92,"⚠️ AT RISK","❌ BELOW")) -> ❌ BELOW
A17: FY 2023 TOTAL | C17: =SUM(C5:C16) -> 22814769 | D17: =SUM(D5:D16) -> 23724190 | E17: =C17-D17 -> -909421 | F17: =IFERROR(C17/D17,0) -> 0.96166693
A20: MARKET SHARE BY SKU CATEGORY
A21: SKU Category | B21: Brand | C21: Net Revenue | D21: Market Share % | E21: Rank | F21: Trend
A22: Cola | B22: =IFERROR(_xlfn.XLOOKUP(A22,'Raw Data'!D:D,'Raw Data'!E:E,"N/A",0,1),"N/A") -> ColaMax | C22: =SUMIF('Raw Data'!D:D,A22,'Raw Data'!K:K) -> 4044721 | D22: =IFERROR(C22/SUM($C$22:$C$27),0) -> 0.17728521 | E22: =RANK(C22,$C$22:$C$27,0) -> 3 | F22: →
A23: Energy Drink | B23: =IFERROR(_xlfn.XLOOKUP(A23,'Raw Data'!D:D,'Raw Data'!E:E,"N/A",0,1),"N/A") -> Monster | C23: =SUMIF('Raw Data'!D:D,A23,'Raw Data'!K:K) -> 5735312 | D23: =IFERROR(C23/SUM($C$22:$C$27),0) -> 0.25138593 | E23: =RANK(C23,$C$22:$C$27,0) -> 1 | F23: ↑
A24: Juice | B24: =IFERROR(_xlfn.XLOOKUP(A24,'Raw Data'!D:D,'Raw Data'!E:E,"N/A",0,1),"N/A") -> Tropika | C24: =SUMIF('Raw Data'!D:D,A24,'Raw Data'!K:K) -> 4472348 | D24: =IFERROR(C24/SUM($C$22:$C$27),0) -> 0.19602863 | E24: =RANK(C24,$C$22:$C$27,0) -> 2 | F24: →
A25: Water | B25: =IFERROR(_xlfn.XLOOKUP(A25,'Raw Data'!D:D,'Raw Data'!E:E,"N/A",0,1),"N/A") -> AquaPure | C25: =SUMIF('Raw Data'!D:D,A25,'Raw Data'!K:K) -> 2830237 | D25: =IFERROR(C25/SUM($C$22:$C$27),0) -> 0.12405284 | E25: =RANK(C25,$C$22:$C$27,0) -> 5 | F25: →
A26: Sports Drink | B26: =IFERROR(_xlfn.XLOOKUP(A26,'Raw Data'!D:D,'Raw Data'!E:E,"N/A",0,1),"N/A") -> PowerX | C26: =SUMIF('Raw Data'!D:D,A26,'Raw Data'!K:K) -> 3223710 | D26: =IFERROR(C26/SUM($C$22:$C$27),0) -> 0.14129926 | E26: =RANK(C26,$C$22:$C$27,0) -> 4 | F26: ↑
A27: Tea | B27: =IFERROR(_xlfn.XLOOKUP(A27,'Raw Data'!D:D,'Raw Data'!E:E,"N/A",0,1),"N/A") -> TeaLeaf | C27: =SUMIF('Raw Data'!D:D,A27,'Raw Data'!K:K) -> 2508441 | D27: =IFERROR(C27/SUM($C$22:$C$27),0) -> 0.10994812 | E27: =RANK(C27,$C$22:$C$27,0) -> 6 | F27: ↓

Sheet Dashboard
A1: BEVERAGES INDIA — MONTHLY CATEGORY MIS REPORT | FY 2023
A2: Prepared by: Saad Memon | Client: Beverages India CPG Portfolio
B5: TOTAL REVENUE | F5: TOP CATEGORY | J5: MARKET LEADER | N5: YTD ATTAINMENT | R5: AVG RATING
B6: =SUMIF('Raw Data'!D:D,"Cola",'Raw Data'!K:K)+SUMIF('Raw Data'!D:D,"Energy Drink",'Raw Data'!K:K)+SUMIF('Raw Data'!D:D,"Juice",'Raw Data'!K:K)+SUMIF('Raw Data'!D:D,"Water",'Raw Data'!K:K)+SUMIF('Raw Data'!D:D,"Sports Drink",'Raw Data'!K:K)+SUMIF('Raw Data'!D:D,"Tea",'Raw Data'!K:K) -> 22814769 | F6: Energy Drink | J6: Monster | N6: ='KPI Tracker'!F17 -> 0.96166693 | R6: 4.3 / 5.0
B7: FY 2023 All Categories | F7: Highest Revenue SKU | J7: Energy Drink Brand | N7: vs Annual Target | R7: Customer Satisfaction
A70: Month | B70: Net Revenue | C70: Target | D70: MoM Growth % | F70: SKU | G70: Revenue | I70: Region | J70: Revenue
A71: ='KPI Tracker'!A5 -> Jan-23 | B71: ='KPI Tracker'!C5 -> 1490482 | C71: ='KPI Tracker'!D5 -> 1490482 | D71: 0 | F71: Cola | G71: =SUMIF('Raw Data'!D:D,F71,'Raw Data'!K:K) -> 4044721 | I71: North India | J71: =SUMIF('Raw Data'!F:F,"North India",'Raw Data'!K:K) -> 6055206
A72: ='KPI Tracker'!A6 -> Feb-23 | B72: ='KPI Tracker'!C6 -> 1455079 | C72: ='KPI Tracker'!D6 -> 1565006 | D72: ='KPI Tracker'!G6 -> -0.023752719 | F72: Energy Drink | G72: =SUMIF('Raw Data'!D:D,F72,'Raw Data'!K:K) -> 5735312 | I72: South India | J72: =SUMIF('Raw Data'!F:F,I72,'Raw Data'!K:K) -> 6135960
A73: ='KPI Tracker'!A7 -> Mar-23 | B73: ='KPI Tracker'!C7 -> 1644055 | C73: ='KPI Tracker'!D7 -> 1643256 | D73: ='KPI Tracker'!G7 -> 0.12987336 | F73: Juice | G73: =SUMIF('Raw Data'!D:D,F73,'Raw Data'!K:K) -> 4472348 | I73: East India | J73: =SUMIF('Raw Data'!F:F,I73,'Raw Data'!K:K) -> 4799750
A74: ='KPI Tracker'!A8 -> Apr-23 | B74: ='KPI Tracker'!C8 -> 1869669 | C74: ='KPI Tracker'!D8 -> 1725419 | D74: ='KPI Tracker'!G8 -> 0.1372302 | F74: Water | G74: =SUMIF('Raw Data'!D:D,F74,'Raw Data'!K:K) -> 2830237 | I74: West India | J74: =SUMIF('Raw Data'!F:F,I74,'Raw Data'!K:K) -> 5823853
A75: ='KPI Tracker'!A9 -> May-23 | B75: ='KPI Tracker'!C9 -> 2139842 | C75: ='KPI Tracker'!D9 -> 1811690 | D75: ='KPI Tracker'!G9 -> 0.14450312 | F75: Sports Drink | G75: =SUMIF('Raw Data'!D:D,F75,'Raw Data'!K:K) -> 3223710
A76: ='KPI Tracker'!A10 -> Jun-23 | B76: ='KPI Tracker'!C10 -> 2441863 | C76: ='KPI Tracker'!D10 -> 1902275 | D76: ='KPI Tracker'!G10 -> 0.14114173 | F76: Tea | G76: =SUMIF('Raw Data'!D:D,F76,'Raw Data'!K:K) -> 2508441
A77: ='KPI Tracker'!A11 -> Jul-23 | B77: ='KPI Tracker'!C11 -> 2324189 | C77: ='KPI Tracker'!D11 -> 1997388 | D77: ='KPI Tracker'!G11 -> -0.048190255
A78: ='KPI Tracker'!A12 -> Aug-23 | B78: ='KPI Tracker'!C12 -> 2268199 | C78: ='KPI Tracker'!D12 -> 2097258 | D78: ='KPI Tracker'!G12 -> -0.024090123
A79: ='KPI Tracker'!A13 -> Sep-23 | B79: ='KPI Tracker'!C13 -> 1972832 | C79: ='KPI Tracker'!D13 -> 2202121 | D79: ='KPI Tracker'!G13 -> -0.13022094
A80: ='KPI Tracker'!A14 -> Oct-23 | B80: ='KPI Tracker'!C14 -> 1850972 | C80: ='KPI Tracker'!D14 -> 2312227 | D80: ='KPI Tracker'!G14 -> -0.061769071
A81: ='KPI Tracker'!A15 -> Nov-23 | B81: ='KPI Tracker'!C15 -> 1631052 | C81: ='KPI Tracker'!D15 -> 2427838 | D81: ='KPI Tracker'!G15 -> -0.11881325
A82: ='KPI Tracker'!A16 -> Dec-23 | B82: ='KPI Tracker'!C16 -> 1726535 | C82: ='KPI Tracker'!D16 -> 2549230 | D82: ='KPI Tracker'!G16 -> 0.058540745
A85: Month | B85: Cola | C85: Energy Drink | D85: Juice | E85: Water | F85: Sports Drink | G85: Tea | I85: SKU | J85: Promo Revenue | K85: Non-Promo Revenue
A86: Jan-23 | B86: 261077 | C86: 397000 | D86: 284656 | E86: 179071 | F86: 203373 | G86: 165305 | I86: Cola | J86: 750586 | K86: 3294135
A87: Feb-23 | B87: 272340 | C87: 351750 | D87: 292880 | E87: 185924 | F87: 193635 | G87: 158550 | I87: Energy Drink | J87: 619437 | K87: 5115875
A88: Mar-23 | B88: 301275 | C88: 398100 | D88: 303532 | E88: 208888 | F88: 250470 | G88: 181790 | I88: Juice | J88: 880268 | K88: 3592080
A89: Apr-23 | B89: 332233 | C89: 475125 | D89: 361084 | E89: 237629 | F89: 250704 | G89: 212894 | I89: Water | J89: 336262 | K89: 2493975
A90: May-23 | B90: 402435 | C90: 522075 | D90: 419840 | E90: 255239 | F90: 308700 | G90: 231553 | I90: Sports Drink | J90: 477990 | K90: 2745720
A91: Jun-23 | B91: 398720 | C91: 629025 | D91: 475220 | E91: 329025 | F91: 348552 | G91: 261321 | I91: Tea | J91: 530766 | K91: 1977675
A92: Jul-23 | B92: 383301 | C92: 579375 | D92: 500960 | E92: 288175 | F92: 322020 | G92: 250358
A93: Aug-23 | B93: 426555 | C93: 582625 | D93: 420364 | E93: 276700 | F93: 322380 | G93: 239575
A94: Sep-23 | B94: 360720 | C94: 503500 | D94: 375060 | E94: 231211 | F94: 278766 | G94: 223575
A95: Oct-23 | B95: 331105 | C95: 451737 | D95: 375320 | E95: 218450 | F95: 258480 | G95: 215880
A96: Nov-23 | B96: 267862 | C96: 403500 | D96: 346640 | E96: 198375 | F96: 235440 | G96: 179235
A97: Dec-23 | B97: 307098 | C97: 441500 | D97: 316792 | E97: 221550 | F97: 251190 | G97: 188405

Sheet Insight Summary
A1: KEY MARKET INSIGHTS — Beverages India FY 2023
A2: Prepared for: Beverages India CPG Portfolio | Analyst: Saad Memon
A4: EXECUTIVE SUMMARY — 5 KEY FINDINGS
A6: 01 | B6: 🚀 REVENUE PEAK — SUMMER SURGE
B7: Energy Drinks and Sports Drinks recorded peak sales in June-July 2023, with combined revenue surging +34% MoM driven by summer seasonality. South India led this growth contributing 28% of total Energy Drink revenue during peak months. Recommend increased shelf allocation and promotional investment in Q2 2024 to capitalize on seasonal demand cycle.
A13: 02 | B13: 👑 MARKET LEADERSHIP — ENERGY DRINK DOMINATES REVENUE
B14: Energy Drink (Monster) leads the portfolio in total revenue despite lower unit volume. At Rs.125 per unit — 5x higher than Water at Rs.25 — Energy Drinks deliver the highest revenue per unit in the portfolio. Shifting 5% of Water shelf space to Energy Drinks could increase category revenue by an estimated 12-15% without additional marketing spend.
A20: 03 | B20: ⚡ CHANNEL INSIGHT — QUICK COMMERCE ACCELERATION
B21: Quick Commerce platforms (Blinkit, Zepto, Swiggy Instamart) are the fastest growing channel for Energy Drinks and Sports Drinks in Tier-1 cities. Traditional Kirana remains dominant for Tea and Water at 45% channel share. Brands targeting young urban consumers should prioritize Q-Commerce as the primary growth lever in FY 2024.
A27: 04 | B27: 🎯 REGIONAL OPPORTUNITY — EAST INDIA UNDERPENETRATED
B28: East India shows the lowest revenue contribution at 22% of total portfolio — 18 percentage points below West India. Energy Drinks and Sports Drinks are particularly underpenetrated in East India at 88% of the all-India index. Expanding distributor partnerships and running regional promotions in East India represents a Rs.2-3 Cr incremental revenue opportunity in FY 2024.
A34: 05 | B34: 📊 ATTAINMENT ALERT — Q4 BELOW TARGET
B35: September through December 2023 came in below revenue target — attainment dropping to 67% in November. Post-monsoon demand slowdown and festive inventory correction drove the shortfall. Portfolio closed FY 2023 at 96.2% of annual target. Recommend front-loading Q1 2024 with trade promotions and early visibility drives to prevent the same seasonal dip.
A42: This report is prepared for client use only. Redistribution without written consent is prohibited. | India Analytics Portfolio Project
